topsis/topsis.py
topsis_Anurag-1.0.0.dist-info/METADATA
topsis_Anurag-1.0.0.dist-info/RECORD
topsis_Anurag-1.0.0.dist-info/WHEEL
topsis_Anurag-1.0.0.dist-info/entry_points.txt
topsis_Anurag-1.0.0.dist-info/top_level.txt
